antiheroes/__init__.py
antiheroes/data.py
antiheroes-0.0.4.dist-info/LICENSE
antiheroes-0.0.4.dist-info/METADATA
antiheroes-0.0.4.dist-info/WHEEL
antiheroes-0.0.4.dist-info/top_level.txt
antiheroes-0.0.4.dist-info/zip-safe
antiheroes-0.0.4.dist-info/RECORD
