Metadata-Version: 2.1
Name: antiheroes
Version: 0.0.4
Summary: Python Library for ANTIHEROES APP
Home-page: https://github.com/yuyatinnefeld/antiheros
Author: yuya tinnefeld
Author-email: yuyatinnefeld@gmail.com
License: Copyright (c) 2022 Yuya Tinnefeld
Project-URL: Bug Tracker, https://github.com/yuyatinnefeld/antiheros/issues
Platform: UNKNOWN
Classifier: Development Status :: 3 - Alpha
Classifier: Programming Language :: Python :: 3.7
Requires-Python: >=3.7
License-File: LICENSE
